./.gitignore
./PKG-INFO
./README.md
./pyproject.toml
./vision_agents/plugins/fast_whisper/__init__.py
./vision_agents/plugins/fast_whisper/stt.py
vision_agents/plugins/fast_whisper/__init__.py
vision_agents/plugins/fast_whisper/stt.py
vision_agents_plugins_fast_whisper-0.2.10.dist-info/METADATA
vision_agents_plugins_fast_whisper-0.2.10.dist-info/WHEEL
vision_agents_plugins_fast_whisper-0.2.10.dist-info/RECORD
