Metadata-Version: 2.4
Name: vision-agents-plugins-fast-whisper
Version: 0.2.10
Summary: Fast Whisper STT integration for Vision Agents
Project-URL: Documentation, https://visionagents.ai/
Project-URL: Website, https://visionagents.ai/
Project-URL: Source, https://github.com/GetStream/Vision-Agents
License-Expression: MIT
Keywords: AI,STT,agents,faster-whisper,speech-to-text,voice agents,whisper
Requires-Python: >=3.10
Requires-Dist: faster-whisper>=1.0.0
Requires-Dist: vision-agents
